{
  "name": "Template 1255",
  "nodes": [
    {
      "parameters": {
        "cronExpression": "*/30 * * * *"
      },
      "name": "Cron",
      "type": "n8n-nodes-base.cron",
      "typeVersion": 1,
      "position": [
        0,
        0
      ]
    },
    {
      "parameters": {},
      "name": "Set",
      "type": "n8n-nodes-base.set",
      "typeVersion": 1,
      "position": [
        300,
        0
      ]
    },
    {
      "parameters": {},
      "name": "Postgres",
      "type": "n8n-nodes-base.postgres",
      "typeVersion": 1,
      "position": [
        600,
        0
      ]
    },
    {
      "parameters": {},
      "name": "MySQL",
      "type": "n8n-nodes-base.mysql",
      "typeVersion": 1,
      "position": [
        900,
        0
      ]
    }
  ],
  "connections": {
    "Cron": {
      "main": [
        [
          {
            "node": "Set",
            "type": "main",
            "index": 0
          }
        ]
      ]
    },
    "Set": {
      "main": [
        [
          {
            "node": "Postgres",
            "type": "main",
            "index": 0
          }
        ]
      ]
    },
    "Postgres": {
      "main": [
        [
          {
            "node": "MySQL",
            "type": "main",
            "index": 0
          }
        ]
      ]
    }
  },
  "active": false,
  "settings": {},
  "id": 1255
}